removedupes/Files.py
removedupes/__init__.py
removedupes/core.py
removedupes-1.0.2.dist-info/METADATA
removedupes-1.0.2.dist-info/RECORD
removedupes-1.0.2.dist-info/WHEEL
removedupes-1.0.2.dist-info/top_level.txt
